{
	"credit": "Made with Blockbench by HeyImBlue3",
	"parent": "minecraft:item/handheld",
	"textures": {
		"layer0": "vampirism:item/hunter_axe_normal"
	},
	"display": {
		"thirdperson_righthand": {
			"rotation": [-45, -90, 0],
			"translation": [0, 6, 1.5],
			"scale": [1.7, 1.7, 0.85]
		},
		"thirdperson_lefthand": {
			"rotation": [-45, 90, 0],
			"translation": [0, 6, 1.5],
			"scale": [1.7, 1.7, 0.85]
		},
		"firstperson_righthand": {
			"rotation": [-45, -90, 0],
			"translation": [0, 8, 1.5],
			"scale": [1.7, 1.7, 0.85]
		},
		"firstperson_lefthand": {
			"rotation": [-45, 90, 0],
			"translation": [0, 8, 1.5],
			"scale": [1.7, 1.7, 0.85]
		},
		"ground": {
			"scale": [1.7, 1.7, 0.85]
		},
		"gui": {
			"scale": [1, 1, 0.5]
		},
		"fixed": {
			"scale": [1, 1, 0.5]
		}
	}
}